nonebot_plugin_group_link_guild/__init__.py
nonebot_plugin_group_link_guild/config.py
nonebot_plugin_group_link_guild/utils.py
nonebot_plugin_group_link_guild-0.0.6.dist-info/LICENSE
nonebot_plugin_group_link_guild-0.0.6.dist-info/METADATA
nonebot_plugin_group_link_guild-0.0.6.dist-info/WHEEL
nonebot_plugin_group_link_guild-0.0.6.dist-info/top_level.txt
nonebot_plugin_group_link_guild-0.0.6.dist-info/RECORD
