Metadata-Version: 2.1
Name: nonebot-plugin-group-link-guild
Version: 0.0.6
Summary: 互通QQ群聊与QQ频道消息的插件
Home-page: https://github.com/17TheWord/nonebot-plugin-group-link-guild
Author: 17TheWord
Author-email: 17theword@gmail.com
License: UNKNOWN
Platform: UNKNOWN
Classifier: Programming Language :: Python :: 3.9
Classifier: License :: OSI Approved :: GNU Affero General Public License v3
Classifier: Operating System :: OS Independent
License-File: LICENSE
Requires-Dist: nonebot2 (>=2.0.0)
Requires-Dist: nonebot-adapter-onebot (>=2.1.1)
Requires-Dist: nonebot-plugin-guild-patch (>=0.2.0)
